cpuinfo/__init__.py
cpuinfo/minicpuinfo.py
minicpuinfo-2.2.0.dist-info/METADATA
minicpuinfo-2.2.0.dist-info/WHEEL
minicpuinfo-2.2.0.dist-info/entry_points.txt
minicpuinfo-2.2.0.dist-info/top_level.txt
minicpuinfo-2.2.0.dist-info/RECORD
