Metadata-Version: 2.1
Name: minicpuinfo
Version: 2.2.0
Summary: minicpu is cpuinfo mini version tool
Author: sahayavalan
Author-email: sahayavalanj1@gmail.com
Requires-Dist: OptionParser
Requires-Dist: psutils
Requires-Dist: pyfiglet
Requires-Dist: setuptools
